inflatox-0.10.1.dist-info/METADATA
inflatox-0.10.1.dist-info/WHEEL
inflatox-0.10.1.dist-info/licenses/LICENSE-EN.txt
inflatox-0.10.1.dist-info/licenses/LICENSE-EUPL.md
inflatox/version.py
inflatox/compiler.py
inflatox/consistency_conditions.py
inflatox/background.py
inflatox/__init__.py
inflatox/symbolic.py
inflatox/libinflx_rs.abi3.so
inflatox-0.10.1.dist-info/RECORD
