Metadata-Version: 2.4
Name: inflatox
Version: 0.10.1
Classifier: Programming Language :: Rust
Classifier: Programming Language :: Python :: 3
Requires-Dist: ipython>=3
Requires-Dist: numpy>=1.16
Requires-Dist: sympy>1
Requires-Dist: joblib>1
Requires-Dist: interruptingcow>=0.8
Requires-Dist: ziglang>=0.10
License-File: LICENSE-EN.txt
License-File: LICENSE-EUPL.md
Summary: Framework for implementing high-performance numerical consistency conditions for multifield inflation models.
Author-email: Raúl Wolters <r.wolters@uu.nl>
License: EUPL-1.2
Requires-Python: >=3.8
Project-URL: Homepage, https://github.com/smups/inflatox
Project-URL: Bug Tracker, https://github.com/smups/inflatox/issues
